MANIFEST.in
setup.py
bin/ezex
ezex/__init__.py
ezex/__main__.py
ezex/dashboard.py
ezex/experiment.py
ezex/folder.py
ezex/run_tb.py
ezex/tensorboard.py
ezex/util.py
ezex.egg-info/PKG-INFO
ezex.egg-info/SOURCES.txt
ezex.egg-info/dependency_links.txt
ezex.egg-info/not-zip-safe
ezex.egg-info/requires.txt
ezex.egg-info/top_level.txt
ezex/default/config.json
ezex/default/dashboard.ipynb