Metadata-Version: 1.0
Name: ezex
Version: 0.2.7
Summary: lightweigt destributed experimentation framework
Home-page: https://github.com/SimonRamstedt/ezex
Author: Simon Ramstedt
Author-email: simonramstedt@gmail.com
License: MIT
Platform: UNKNOWN
